Metadata-Version: 2.1
Name: straighten
Version: 0.2.0
Summary: UNKNOWN
Home-page: https://github.com/neuro-ml/straighten
Download-URL: https://github.com/neuro-ml/straighten/archive/v0.2.0.tar.gz
License: MIT
Keywords: data,version control
Platform: UNKNOWN
Classifier: Programming Language :: Python :: 3.6
Classifier: Programming Language :: Python :: 3.7
Classifier: Programming Language :: Python :: 3.8
Classifier: Programming Language :: Python :: 3.9
Classifier: Programming Language :: Python :: 3.10
License-File: LICENSE
